odoo/addons/shopfloor_example/README.rst
odoo/addons/shopfloor_example/__init__.py
odoo/addons/shopfloor_example/__manifest__.py
odoo/addons/shopfloor_example/actions/__init__.py
odoo/addons/shopfloor_example/actions/data.py
odoo/addons/shopfloor_example/actions/data_detail.py
odoo/addons/shopfloor_example/actions/schema.py
odoo/addons/shopfloor_example/actions/schema_detail.py
odoo/addons/shopfloor_example/actions/search.py
odoo/addons/shopfloor_example/components/__init__.py
odoo/addons/shopfloor_example/components/scan_handler_partner.py
odoo/addons/shopfloor_example/demo/shopfloor_menu_demo.xml
odoo/addons/shopfloor_example/demo/shopfloor_profile_demo.xml
odoo/addons/shopfloor_example/demo/shopfloor_scenario_demo.xml
odoo/addons/shopfloor_example/i18n/es_AR.po
odoo/addons/shopfloor_example/i18n/shopfloor_example.pot
odoo/addons/shopfloor_example/readme/CONTRIBUTORS.rst
odoo/addons/shopfloor_example/readme/CREDITS.rst
odoo/addons/shopfloor_example/readme/DESCRIPTION.rst
odoo/addons/shopfloor_example/readme/HISTORY.rst
odoo/addons/shopfloor_example/readme/ROADMAP.rst
odoo/addons/shopfloor_example/services/__init__.py
odoo/addons/shopfloor_example/services/partner_service.py
odoo/addons/shopfloor_example/static/description/icon.png
odoo/addons/shopfloor_example/static/description/index.html
odoo/addons/shopfloor_example/static/wms/src/components/detail/detail_partner.js
odoo/addons/shopfloor_example/static/wms/src/scenario/checkout.js
odoo/addons/shopfloor_example/static/wms/src/scenario/partner.js
odoo/addons/shopfloor_example/templates/assets.xml
odoo/addons/shopfloor_example/tests/__init__.py
odoo/addons/shopfloor_example/tests/test_partner_service.py
odoo/addons/shopfloor_example/tests/test_scan_anything.py
odoo13_addon_shopfloor_example-13.0.1.0.1.dist-info/METADATA
odoo13_addon_shopfloor_example-13.0.1.0.1.dist-info/WHEEL
odoo13_addon_shopfloor_example-13.0.1.0.1.dist-info/top_level.txt
odoo13_addon_shopfloor_example-13.0.1.0.1.dist-info/RECORD
