Metadata-Version: 2.1
Name: odoo13-addon-shopfloor-example
Version: 13.0.1.0.1
Summary: Show how to customize the Shopfloor app frontend.
Home-page: https://github.com/OCA/wms
Author: Camptocamp, ACSONE, Odoo Community Association (OCA)
Author-email: support@odoo-community.org
License: AGPL-3
Platform: UNKNOWN
Classifier: Programming Language :: Python
Classifier: Framework :: Odoo
Classifier: License :: OSI Approved :: GNU Affero General Public License v3
Requires-Python: >=3.5
Requires-Dist: odoo13-addon-shopfloor-base
Requires-Dist: odoo13-addon-shopfloor-mobile-base
Requires-Dist: odoo (<13.1dev,>=13.0a)
